	{ "pxObjClass":"BV-BVTI-Int-GMUD-Manual-Response" ,"JornadaTech":{ "keyJiraForumTatico":"ARQCOR-3087" ,"Nome":"[Débitos Veiculares] - Consulta de débitos" ,"PassarForumArquitetura":"Sim" ,"pxObjClass":"BV-BVTI-Int-GMUD-JornadaTech" ,"pyID":"JT-189266" ,"status":"Pending-Execucao" ,"Ciclos":[ { "Nome":"teste" ,"pxObjClass":"BV-BVTI-Int-GMUD-Ciclo" ,"pyID":"JTCD-92002" ,"status":"Pending-Implantacao" ,"Links":[ { "pxObjClass":"BV-BVTI-Int-GMUD-Link" ,"pyURLType":"Evidência Homologação da Mudança" } ] } ] } ,"Messages":[ { "Codigo":"10" ,"Descricao":"Jornada Tech disponível para GMUD manual" ,"pxObjClass":"BV-BVTI-Int-GMUD-Mensagem" } ] }